doc_utils
tests
