Metadata-Version: 1.2
Name: doc-utils
Version: 0.0.2
Summary: Utilities for docx, xlsx and pdf froms templating
Home-page: https://github.com/a-ader/doc-utils
Author: Aleksandr Ader
Author-email: info@ader-design.ee
License: UNKNOWN
Platform: UNKNOWN
Classifier: Programming Language :: Python :: 3
Classifier: License :: OSI Approved :: MIT License
Classifier: Operating System :: OS Independent
Requires-Python: >=3.6
